neaktor/__init__.py
neaktor/api.py
neaktor/constants.py
neaktor/exceptions.py
neaktor/objects.py
python_neaktor_api-2.0.0.dist-info/METADATA
python_neaktor_api-2.0.0.dist-info/WHEEL
python_neaktor_api-2.0.0.dist-info/licenses/LICENCE
python_neaktor_api-2.0.0.dist-info/RECORD
