Metadata-Version: 2.3
Name: python-neaktor-api
Version: 2.0.0
Summary: Package to interact with neaktor API
Project-URL: Homepage, https://github.com/tkvitko/python-neaktor-api
Project-URL: Issues, https://github.com/tkvitko/python-neaktor-api/issues
Author-email: Taras Kvitko <tkvitko@gmail.com>
License-File: LICENCE
Classifier: License :: OSI Approved :: MIT License
Classifier: Operating System :: OS Independent
Classifier: Programming Language :: Python :: 3
Requires-Python: >=3.8
